dltkdl/__init__.py
dltkdl/core.py
dltkdl/data.py
dltkdl/imports.py
dltkdl/models.py
dltkdl/predictor.py
dltkdl/preprocessor.py
dltkdl/utils.py
dltkdl/version.py
dltkdl/optimizer/__init__.py
dltkdl/optimizer/lrfinder.py
dltkdl/optimizer/optimization.py
dltkdl/optimizer/sgdr.py
dltkdl/optimizer/triangular.py
dltkdl/tabledata/__init__.py
dltkdl/tabledata/data.py
dltkdl/tabledata/models.py
dltkdl/tabledata/predictor.py
dltkdl/tabledata/preprocessor.py
dltkdl/text/__init__.py
dltkdl/text/data.py
dltkdl/text/eda.py
dltkdl/text/learner.py
dltkdl/text/models.py
dltkdl/text/predictor.py
dltkdl/text/preprocessor.py
dltkdl/text/textutils.py
dltkdl/text/ner/__init__.py
dltkdl/text/ner/data.py
dltkdl/text/ner/learner.py
dltkdl/text/ner/models.py
dltkdl/text/ner/predictor.py
dltkdl/text/ner/preprocessor.py
dltkdl/text/ner/anago/__init__.py
dltkdl/text/ner/anago/callbacks.py
dltkdl/text/ner/anago/layers.py
dltkdl/text/ner/anago/layers_standalone.py
dltkdl/text/ner/anago/models.py
dltkdl/text/ner/anago/preprocessing.py
dltkdl/text/ner/anago/tagger.py
dltkdl/text/ner/anago/trainer.py
dltkdl/text/ner/anago/utils.py
dltkdl/text/ner/anago/wrapper.py
dltkdl/text/qa/__init__.py
dltkdl/text/qa/core.py
dltkdl/text/shallownlp/__init__.py
dltkdl/text/shallownlp/classifier.py
dltkdl/text/shallownlp/imports.py
dltkdl/text/shallownlp/ner.py
dltkdl/text/shallownlp/searcher.py
dltkdl/text/shallownlp/utils.py
dltkdl/text/shallownlp/version.py
dltkdl/text/summarization/__init__.py
dltkdl/text/summarization/core.py
dltkdl/text/translation/__init__.py
dltkdl/text/translation/core.py
dltkdl/text/zsl/__init__.py
dltkdl/text/zsl/core.py
dltkdl/vision/__init__.py
dltkdl/vision/data.py
dltkdl/vision/learner.py
dltkdl/vision/models.py
dltkdl/vision/predictor.py
dltkdl/vision/preprocessor.py
dltkdl/vision/wrn.py
DLTKDL-51.0.8.dist-info/LICENSE
DLTKDL-51.0.8.dist-info/METADATA
DLTKDL-51.0.8.dist-info/WHEEL
DLTKDL-51.0.8.dist-info/top_level.txt
DLTKDL-51.0.8.dist-info/RECORD
