Metadata-Version: 2.1
Name: DLTKDL
Version: 51.0.8
Summary: DLTKDL is a wrapper for TensorFlow and Keras that makes deep learning and AI more accessible and easier to apply
Home-page: https://github.com/dltk-ai/Deep-Learning
Author: DLTK
Author-email: connect@qubitai.tech
License: GPL-3.0 License
Keywords: tensorflow,keras,deep learning,machine learning
Platform: UNKNOWN
Classifier: Development Status :: 4 - Beta
Classifier: Intended Audience :: Developers
Classifier: Topic :: Scientific/Engineering :: Artificial Intelligence
Classifier: License :: OSI Approved :: Apache Software License
Classifier: Programming Language :: Python :: 3.6
Classifier: Programming Language :: Python :: 3.7
Classifier: Programming Language :: Python :: 3.8
Requires-Dist: tensorflow (==2.3.0)
Requires-Dist: scipy (==1.5.2)
Requires-Dist: matplotlib
Requires-Dist: pandas (==1.0.1)
Requires-Dist: fastprogress (==0.1.21)
Requires-Dist: keras-bert (==0.86.0)
Requires-Dist: requests
Requires-Dist: joblib
Requires-Dist: langdetect
Requires-Dist: theano
Requires-Dist: jieba
Requires-Dist: cchardet
Requires-Dist: networkx
Requires-Dist: bokeh
Requires-Dist: seqeval (==0.0.19)
Requires-Dist: packaging
Requires-Dist: transformers (==3.1.0)
Requires-Dist: ipython
Requires-Dist: syntok
Requires-Dist: whoosh
Requires-Dist: scikit-learn
Requires-Dist: numba
